__init__.py
wayback_utils.py
wayback_utils-0.1.8.dist-info/licenses/LICENSE
wayback_utils-0.1.8.dist-info/METADATA
wayback_utils-0.1.8.dist-info/WHEEL
wayback_utils-0.1.8.dist-info/top_level.txt
wayback_utils-0.1.8.dist-info/RECORD
