Metadata-Version: 2.4
Name: wayback_utils
Version: 0.1.8
Summary: Wayback Machine utils (web.archive.org)
Author-email: melon-dog <JackTezos@proton.me>
License: MIT License
Project-URL: Homepage, https://github.com/melon-dog/wayback_utils
Classifier: License :: OSI Approved :: MIT License
Classifier: Programming Language :: Python :: 3
Requires-Python: >=3.10
License-File: LICENSE
Requires-Dist: requests>=2.25.1
Dynamic: license-file
